snap7/__init__.py
snap7/client.py
snap7/common.py
snap7/error.py
snap7/logo.py
snap7/partner.py
snap7/protocol.py
snap7/protocol.pyi
snap7/py.typed
snap7/type.py
snap7/lib/libsnap7.dylib
snap7/server/__init__.py
snap7/server/__main__.py
snap7/util/__init__.py
snap7/util/db.py
snap7/util/getters.py
snap7/util/setters.py
python_snap7-2.0.2.dist-info/LICENSE
python_snap7-2.0.2.dist-info/METADATA
python_snap7-2.0.2.dist-info/WHEEL
python_snap7-2.0.2.dist-info/entry_points.txt
python_snap7-2.0.2.dist-info/top_level.txt
python_snap7-2.0.2.dist-info/RECORD
