Metadata-Version: 2.1
Name: python-snap7
Version: 2.0.2
Summary: Python wrapper for the snap7 library
Author-email: Gijs Molenaar <gijsmolenaar@gmail.com>
License: MIT License
Project-URL: Homepage, https://github.com/gijzelaerr/python-snap7
Project-URL: Documentation, https://python-snap7.readthedocs.io/en/latest/
Keywords: snap7,s7,siemens,plc
Classifier: Development Status :: 5 - Production/Stable
Classifier: Environment :: Console
Classifier: Topic :: System :: Hardware
Classifier: Intended Audience :: Developers
Classifier: Intended Audience :: Manufacturing
Classifier: License :: OSI Approved :: MIT License
Classifier: Operating System :: POSIX
Classifier: Programming Language :: Python :: 3.9
Classifier: Programming Language :: Python :: 3.10
Classifier: Programming Language :: Python :: 3.11
Classifier: Programming Language :: Python :: 3.12
Classifier: Programming Language :: Python :: 3.13
Requires-Python: >=3.9
License-File: LICENSE
Provides-Extra: test
Requires-Dist: pytest; extra == "test"
Requires-Dist: mypy; extra == "test"
Requires-Dist: types-setuptools; extra == "test"
Requires-Dist: ruff; extra == "test"
Requires-Dist: tox; extra == "test"
Requires-Dist: types-click; extra == "test"
Requires-Dist: uv; extra == "test"
Provides-Extra: cli
Requires-Dist: rich; extra == "cli"
Requires-Dist: click; extra == "cli"
Provides-Extra: doc
Requires-Dist: sphinx; extra == "doc"
Requires-Dist: sphinx_rtd_theme; extra == "doc"
